django_logic_celery/__init__.py
django_logic_celery/commands.py
django_logic_celery/transitions.py
django_logic_celery-0.0.9.dist-info/LICENSE
django_logic_celery-0.0.9.dist-info/METADATA
django_logic_celery-0.0.9.dist-info/WHEEL
django_logic_celery-0.0.9.dist-info/top_level.txt
django_logic_celery-0.0.9.dist-info/RECORD
