Metadata-Version: 2.1
Name: django-logic-celery
Version: 0.0.9
Summary: Django Logic Celery - background transitions
Home-page: https://github.com/Borderless360/django-logic-celery
Author: Emil Balashov
Author-email: emil@borderless360.com
License: MIT License
Keywords: django
Platform: any
Classifier: Development Status :: 1 - Planning
Classifier: Programming Language :: Python :: 3
Classifier: License :: OSI Approved :: MIT License
Classifier: Operating System :: OS Independent
Classifier: Intended Audience :: Developers
Classifier: Framework :: Django
Classifier: Framework :: Django :: 2.0
Classifier: Framework :: Django :: 2.1
Classifier: Framework :: Django :: 2.2
Classifier: Programming Language :: Python
Classifier: Programming Language :: Python :: 3
Classifier: Programming Language :: Python :: 3.6
Classifier: Programming Language :: Python :: 3.7
Classifier: Topic :: Software Development :: Libraries :: Python Modules
Requires-Python: >=3.6
